dutate/__init__.py
dutate/dutate.py
dutate-0.1.dist-info/METADATA
dutate-0.1.dist-info/WHEEL
dutate-0.1.dist-info/top_level.txt
dutate-0.1.dist-info/RECORD
