Metadata-Version: 2.1
Name: dutate
Version: 0.1
Summary: Python client for dutate.com
Home-page: https://gitlab.com/dutate-plugins/python_client
Author: Doniyor Jurabayev
Author-email: behconsci@gmail.com
License: UNKNOWN
Download-URL: https://gitlab.com/dutate-plugins/python_client/blob/master/dist/dutate-0.1.tar.gz
Keywords: track,monitor,bug
Platform: UNKNOWN
Requires-Dist: requests
